MANIFEST.in
README.md
doc.md
setup.py
the_rack/__init__.py
the_rack/core.py
the_rack.egg-info/PKG-INFO
the_rack.egg-info/SOURCES.txt
the_rack.egg-info/dependency_links.txt
the_rack.egg-info/top_level.txt