Metadata-Version: 1.1
Name: the-rack
Version: 1.0.1
Summary: A cachable collection with extension abilities
Home-page: http://github.com/tleb/the_rack
Author: tleb
Author-email: tleb@openmailbox.org
License: UNKNOWN
Platform: UNKNOWN
Classifier: Programming Language :: Python
Classifier: License :: OSI Approved :: MIT License
Classifier: Operating System :: OS Independent
Classifier: Programming Language :: Python :: 3.4
